{
  "slug": "our-clients",
  "title_en": "Our Clients",
  "title_he": "הלקוחות שלנו",
  "description_en": "Dynamic client logo grid with bilingual support (English & Hebrew) and responsive design",
  "description_he": "רשת לוגו דינמית של לקוחות עם תמיכה דו-לשונית (אנגלית וערבית) ועיצוב תגובתי",
  "og_type": "website",
  "section": "main",
  "pages": {
    "b2b": {
      "heading_en": "Our Clients",
      "heading_he": "הלקוחות שלנו",
      "subtitle_en": "From small to global, we have partnered with some great companies",
      "subtitle_he": "מחברות קטנות ועד גלובליות, שיתפנו פעולה עם חברות מעולות",
      "assetPath": "/assets/b2b",
      "clients_en": [
        "Microsoft", "American Express", "Nielsen", "Human Ventures",
        "Passport", "JFrog", "Alam", "Taboola", "Israeli Tech", "Startupin", "Playtika", "Finaro"
      ]
    },
    "b2c": {
      "heading_en": "Our Clients",
      "heading_he": "הלקוחות שלנו",
      "subtitle_en": "Trusted by leading B2C brands worldwide",
      "subtitle_he": "מהימן על ידי מותגי B2C מובילים ברחבי העולם",
      "assetPath": "/assets/b2c",
      "clients_en": [
        "Client 1", "Client 2", "Client 3", "Client 4",
        "Client 5", "Client 6", "Client 7", "Client 8", "Client 9", "Client 10", "Client 11", "Client 12"
      ]
    },
    "cyber-security": {
      "heading_en": "Our Clients",
      "heading_he": "הלקוחות שלנו",
      "subtitle_en": "Trusted by enterprise cybersecurity leaders",
      "subtitle_he": "מהימן על ידי מנהיגי אבטחת סייבר בעלות עסקית",
      "assetPath": "/assets/cyber-security",
      "clients_en": [
        "Fortune 500 Companies", "Enterprise Clients", "Security Leaders", "Enterprise Platforms",
        "Global Enterprises", "Tech Leaders", "Security First", "Enterprise Grade",
        "Leading Platforms", "Top Enterprise", "Global Security", "Security Solutions"
      ]
    },
    "fintech-finance": {
      "heading_en": "Our Clients",
      "heading_he": "הלקוחות שלנו",
      "subtitle_en": "Powering fintech innovation for leading financial companies",
      "subtitle_he": "הנעת חדשנות פינטק לחברות פיננסיות מובילות",
      "assetPath": "/assets/fintech-finance",
      "clients_en": [
        "Financial Leaders", "Fintech Innovators", "Banking Platforms", "Payment Processors",
        "Trading Platforms", "Crypto Exchanges", "Investment Firms", "Financial Services",
        "Digital Banking", "Fintech Unicorns", "Payment Leaders", "Finance Platforms"
      ]
    },
    "gaming": {
      "heading_en": "Our Clients",
      "heading_he": "הלקוחות שלנו",
      "subtitle_en": "Trusted by gaming studios and game publishers worldwide",
      "subtitle_he": "מהימן על ידי סטודיוי משחקים ומפיצי משחקים ברחבי העולם",
      "assetPath": "/assets/gaming",
      "clients_en": [
        "AAA Studios", "Indie Developers", "Game Publishers", "Esports Platforms",
        "Gaming Networks", "Game Engines", "Streaming Platforms", "Gaming Companies",
        "Mobile Game Dev", "Game Distribution", "Gaming Platforms", "Game Leaders"
      ]
    },
    "medical-healthcare": {
      "heading_en": "Our Clients",
      "heading_he": "הלקוחות שלנו",
      "subtitle_en": "Trusted by healthcare providers and medical innovators",
      "subtitle_he": "מהימן על ידי ספקי שירויות בריאות וחדשנים רפואיים",
      "assetPath": "/assets/medical-healthcare",
      "clients_en": [
        "Hospital Networks", "Healthcare Providers", "Medical Tech", "Pharma Companies",
        "Telemedicine Platforms", "Medical Devices", "Health Insurance", "Biotech Firms",
        "Clinical Labs", "Healthcare Systems", "Medical Solutions", "Health Tech"
      ]
    },
    "agritech": {
      "heading_en": "Our Clients",
      "heading_he": "הלקוחות שלנו",
      "subtitle_en": "Partnering with leading agritech companies globally",
      "subtitle_he": "שיתוף פעולה עם חברות אגריטק מובילות ברחבי העולם",
      "assetPath": "/assets/agritech",
      "clients_en": [
        "Agritech Leaders", "Farm Tech", "Precision Agriculture", "Crop Management",
        "Farming Solutions", "Agricultural Data", "Soil Tech", "Harvest Platforms",
        "Climate Smart", "Agri Innovation", "Farm Software", "Agriculture Systems"
      ]
    },
    "saas-platforms": {
      "heading_en": "Our Clients",
      "heading_he": "הלקוחות שלנו",
      "subtitle_en": "Powering SaaS platforms for thousands of businesses",
      "subtitle_he": "הנעת פלטפורמות SaaS לאלפי עסקים",
      "assetPath": "/assets/saas-platforms",
      "clients_en": [
        "Enterprise SaaS", "B2B Platforms", "Workflow Tools", "Collaboration Apps",
        "Productivity Suites", "CRM Platforms", "Analytics Tools", "Cloud Services",
        "Integration Platforms", "Automation Tools", "Data Platforms", "SaaS Leaders"
      ]
    },
    "device-iot": {
      "heading_en": "Our Clients",
      "heading_he": "הלקוחות שלנו",
      "subtitle_en": "Powering IoT solutions for connected device manufacturers",
      "subtitle_he": "הנעת פתרונות IoT ליצרני התקנים מחוברים",
      "assetPath": "/assets/device-iot",
      "clients_en": [
        "IoT Manufacturers", "Smart Device Makers", "Connected Hardware", "IoT Platforms",
        "Sensor Tech", "Smart Home", "Industrial IoT", "Connected Vehicles",
        "Wearables", "Smart Cities", "Device Networks", "IoT Solutions"
      ]
    },
    "mobile-apps": {
      "heading_en": "Our Clients",
      "heading_he": "הלקוחות שלנו",
      "subtitle_en": "Trusted by app developers and mobile platforms",
      "subtitle_he": "מהימן על ידי מפתחי אפליקציות וplatforms ניידות",
      "assetPath": "/assets/mobile-apps",
      "clients_en": [
        "App Developers", "Mobile App Studios", "Social Networks", "Messaging Apps",
        "Dating Platforms", "Fitness Apps", "Travel Apps", "E-Commerce Apps",
        "Gaming Apps", "Productivity Apps", "Utility Apps", "Mobile Leaders"
      ]
    },
    "startups-tech": {
      "heading_en": "Our Clients",
      "heading_he": "הלקוחות שלנו",
      "subtitle_en": "Partnering with innovative tech startups",
      "subtitle_he": "שיתוף פעולה עם סטארטאפים טכנולוגיים חדשניים",
      "assetPath": "/assets/startups-tech",
      "clients_en": [
        "Series A Startups", "Series B/C", "Tech Unicorns", "AI Startups",
        "Blockchain Startups", "Climate Tech", "Deeptech Firms", "Venture Backed",
        "Emerging Tech", "Innovation Labs", "Tech Disruptors", "Future Leaders"
      ]
    },
    "dev": {
      "heading_en": "Our Clients",
      "heading_he": "הלקוחות שלנו",
      "subtitle_en": "Trusted by developer tools and developer platform companies",
      "subtitle_he": "מהימן על ידי כלים למפתחים וחברות פלטפורמות מפתחים",
      "assetPath": "/assets/dev",
      "clients_en": [
        "Development Platforms", "Code Editors", "CI/CD Tools", "DevOps Solutions",
        "Testing Tools", "Deployment Platforms", "Monitoring Tools", "Security Tools",
        "API Platforms", "Developer Networks", "Code Management", "Dev Tools Leaders"
      ]
    }
  }
}
